hug_authentication_ldap
